Workbook

Sheet Cover
A1: Compliance services value model
A2: A risk-based business case for renewing compliance support at a fictional multi-academy trust.
A4: Scenario: Northfield Learning Trust (fictional, six schools) has a new business manager reviewing budgets. They plan to cancel fire safety, health and safety, and data protection support.
A5: The model compares three options over three years: keep the service, bring compliance in-house, or cancel with no replacement.
A7: How to use
A8: 1. Change blue cells on the Inputs sheet. Yellow cells are the key assumptions to agree with the customer.
A9: 2. Pick a scenario on Inputs (1 = Conservative, 2 = Expected, 3 = High).
A10: 3. Read results on the Summary sheet. Actions lists the outstanding audit actions that drive risk exposure.
A12: Colour key: blue = input, black = formula, green = link to another sheet, yellow fill = key assumption.
A14: Important: the organisation, actions and all figures are fictional and illustrative. Enforcement probabilities and impacts are modelling assumptions, not legal advice or real penalty data.
A15: Built by Chelsea Alagoa as a portfolio example of value assessment and ROI/TCO modelling.

Sheet Summary
A1: Summary
A3: Outstanding actions
A4: Total outstanding actions | B4: =COUNTA(Actions!A2:A19) -> 18
A5: High-risk actions | B5: =COUNTIF(Actions!E2:E19,"High") -> 8
A6: Actions with no owner assigned | B6: =COUNTIF(Actions!G2:G19,"No") -> 14
A8: Annual risk exposure if the trust cancels (by scenario)
B9: Conservative | C9: Expected | D9: High
A10: Risk exposure per year | B10: =Actions!L20 -> 8075 | C10: =Actions!M20 -> 20925 | D10: =Actions!N20 -> 42175
A11: Annual service fees | B11: =Inputs!$B$21 -> 11000 | C11: =Inputs!$B$21 -> 11000 | D11: =Inputs!$B$21 -> 11000
A12: Exposure for every £1 of fees | B12: =IFERROR(B10/B11,0) -> 0.73409091 | C12: =IFERROR(C10/C11,0) -> 1.9022727 | D12: =IFERROR(D10/D11,0) -> 3.8340909
A13: Year 1 ROI of keeping the service | B13: =IFERROR((B10*Inputs!$B$25+Inputs!$B$34*(Inputs!$B$37-Inputs!$B$35)*12-Inputs!$B$21)/Inputs!$B$21,0) -> -0.18363636 | C13: =IFERROR((C10*Inputs!$B$25+Inputs!$B$34*(Inputs!$B$37-Inputs!$B$35)*12-Inputs!$B$21)/Inputs!$B$21,0) -> 0.75090909 | D13: =IFERROR((D10*Inputs!$B$25+Inputs!$B$34*(Inputs!$B$37-Inputs!$B$35)*12-Inputs!$B$21)/Inputs!$B$21,0) -> 2.2963636
A15: Three-year comparison (selected scenario)
A16: Option | B16: 3-year total cost | C16: vs keeping provider
A17: A: keep provider support | B17: =Options_3yr!E10 -> 49074.9 | C17: =B17-$B$17 -> 0
A18: B: bring compliance in-house | B18: =Options_3yr!E17 -> 103267.5 | C18: =B18-$B$17 -> 54192.6
A19: C: cancel with no replacement | B19: =Options_3yr!E22 -> 72855 | C19: =B19-$B$17 -> 23780.1
A21: Payback on Year 1 fees (months), selected scenario | B21: =IFERROR(Inputs!$B$21/((CHOOSE(Inputs!$B$3,B10,C10,D10)*Inputs!$B$25+Inputs!$B$34*(Inputs!$B$37-Inputs!$B$35)*12)/12),0) -> 6.8535826
A23: Reading the result: compare the fees with the exposure they remove, then agree the yellow assumptions with the customer before presenting.
A24: All figures are fictional and illustrative.

Sheet Inputs
A1: Inputs and assumptions
A3: Scenario selected (1 = Conservative, 2 = Expected, 3 = High) | B3: 2 | C3: Drives the Options and Summary sheets.
A5: Probability an unresolved action leads to enforcement within 12 months
A6: Risk rating | B6: Conservative | C6: Expected | D6: High
A7: High | B7: 0.02 | C7: 0.05 | D7: 0.1 | E7: Illustrative assumption. Agree with the customer and their insurer or adviser.
A8: Medium | B8: 0.005 | C8: 0.015 | D8: 0.03
A9: Low | B9: 0 | C9: 0 | D9: 0.005
A11: Financial impact per enforcement event (fine, legal costs, remediation)
A12: Service area | B12: Impact (£)
A13: Fire safety | B13: 50000 | C13: Illustrative. Fire safety offences can attract unlimited fines, so this is deliberately conservative.
A14: Health and safety | B14: 40000
A15: Data protection | B15: 25000
A17: Annual service fees (£)
A18: Fire safety support | B18: 3500
A19: Health and safety support | B19: 4500
A20: Data protection officer service | B20: 3000
A21: Total annual fees | B21: =SUM(B18:B20) -> 11000
A22: Annual fee uplift | B22: 0.03
A24: Risk reduction
A25: Share of risk removed with provider support | B25: 0.8 | C25: Assumes high-risk actions are closed with specialist advice and tracked in a dashboard.
A26: Share of risk removed with an in-house approach | B26: 0.5 | C26: Lower than provider support: less specialist knowledge and no external audit.
A28: In-house option costs
A29: Compliance officer salary, fully loaded (£) | B29: 48000
A30: Share of a full-time role needed | B30: 0.4
A31: Training and tools per year (£) | B31: 3500
A33: Business manager time
A34: Hourly cost, fully loaded (£) | B34: 35
A35: Hours per month: keep provider | B35: 2
A36: Hours per month: in-house | B36: 3
A37: Hours per month: cancel with no replacement | B37: 8 | C37: Chasing actions, finding guidance and responding to incidents without support.
A39: All figures are fictional and illustrative.

Sheet Actions
A1: action_id | B1: school | C1: service_area | D1: action | E1: risk_rating | F1: days_overdue | G1: owner_assigned | H1: Prob. conservative | I1: Prob. expected | J1: Prob. high | K1: Impact (£) | L1: Expected loss conservative (£) | M1: Expected loss expected (£) | N1: Expected loss high (£) | O1: Expected loss selected (£)
A2: FS-01 | B2: Ashgrove Primary | C2: Fire safety | D2: Fire door self-closers missing on two classroom doors | E2: High | F2: 142 | G2: No | H2: =INDEX(Inputs!$B$7:$B$9,MATCH(E2,Inputs!$A$7:$A$9,0)) -> 0.02 | I2: =INDEX(Inputs!$C$7:$C$9,MATCH(E2,Inputs!$A$7:$A$9,0)) -> 0.05 | J2: =INDEX(Inputs!$D$7:$D$9,MATCH(E2,Inputs!$A$7:$A$9,0)) -> 0.1 | K2: =INDEX(Inputs!$B$13:$B$15,MATCH(C2,Inputs!$A$13:$A$15,0)) -> 50000 | L2: =H2*K2 -> 1000 | M2: =I2*K2 -> 2500 | N2: =J2*K2 -> 5000 | O2: =CHOOSE(Inputs!$B$3,L2,M2,N2) -> 2500
A3: FS-02 | B3: Beacon Hill Academy | C3: Fire safety | D3: Fire risk assessment overdue for review | E3: High | F3: 95 | G3: No | H3: =INDEX(Inputs!$B$7:$B$9,MATCH(E3,Inputs!$A$7:$A$9,0)) -> 0.02 | I3: =INDEX(Inputs!$C$7:$C$9,MATCH(E3,Inputs!$A$7:$A$9,0)) -> 0.05 | J3: =INDEX(Inputs!$D$7:$D$9,MATCH(E3,Inputs!$A$7:$A$9,0)) -> 0.1 | K3: =INDEX(Inputs!$B$13:$B$15,MATCH(C3,Inputs!$A$13:$A$15,0)) -> 50000 | L3: =H3*K3 -> 1000 | M3: =I3*K3 -> 2500 | N3: =J3*K3 -> 5000 | O3: =CHOOSE(Inputs!$B$3,L3,M3,N3) -> 2500
A4: FS-03 | B4: Danbury Secondary | C4: Fire safety | D4: Fire door intumescent strips damaged in science block | E4: High | F4: 120 | G4: No | H4: =INDEX(Inputs!$B$7:$B$9,MATCH(E4,Inputs!$A$7:$A$9,0)) -> 0.02 | I4: =INDEX(Inputs!$C$7:$C$9,MATCH(E4,Inputs!$A$7:$A$9,0)) -> 0.05 | J4: =INDEX(Inputs!$D$7:$D$9,MATCH(E4,Inputs!$A$7:$A$9,0)) -> 0.1 | K4: =INDEX(Inputs!$B$13:$B$15,MATCH(C4,Inputs!$A$13:$A$15,0)) -> 50000 | L4: =H4*K4 -> 1000 | M4: =I4*K4 -> 2500 | N4: =J4*K4 -> 5000 | O4: =CHOOSE(Inputs!$B$3,L4,M4,N4) -> 2500
A5: FS-04 | B5: Fernwood Academy | C5: Fire safety | D5: Emergency lighting test records incomplete | E5: Medium | F5: 60 | G5: Yes | H5: =INDEX(Inputs!$B$7:$B$9,MATCH(E5,Inputs!$A$7:$A$9,0)) -> 0.005 | I5: =INDEX(Inputs!$C$7:$C$9,MATCH(E5,Inputs!$A$7:$A$9,0)) -> 0.015 | J5: =INDEX(Inputs!$D$7:$D$9,MATCH(E5,Inputs!$A$7:$A$9,0)) -> 0.03 | K5: =INDEX(Inputs!$B$13:$B$15,MATCH(C5,Inputs!$A$13:$A$15,0)) -> 50000 | L5: =H5*K5 -> 250 | M5: =I5*K5 -> 750 | N5: =J5*K5 -> 1500 | O5: =CHOOSE(Inputs!$B$3,L5,M5,N5) -> 750
A6: FS-05 | B6: Cedar Vale Primary | C6: Fire safety | D6: Fire drill not logged for spring term | E6: Medium | F6: 45 | G6: No | H6: =INDEX(Inputs!$B$7:$B$9,MATCH(E6,Inputs!$A$7:$A$9,0)) -> 0.005 | I6: =INDEX(Inputs!$C$7:$C$9,MATCH(E6,Inputs!$A$7:$A$9,0)) -> 0.015 | J6: =INDEX(Inputs!$D$7:$D$9,MATCH(E6,Inputs!$A$7:$A$9,0)) -> 0.03 | K6: =INDEX(Inputs!$B$13:$B$15,MATCH(C6,Inputs!$A$13:$A$15,0)) -> 50000 | L6: =H6*K6 -> 250 | M6: =I6*K6 -> 750 | N6: =J6*K6 -> 1500 | O6: =CHOOSE(Inputs!$B$3,L6,M6,N6) -> 750
A7: FS-06 | B7: Elmfield Primary | C7: Fire safety | D7: Evacuation plan for wheelchair user not documented | E7: High | F7: 80 | G7: No | H7: =INDEX(Inputs!$B$7:$B$9,MATCH(E7,Inputs!$A$7:$A$9,0)) -> 0.02 | I7: =INDEX(Inputs!$C$7:$C$9,MATCH(E7,Inputs!$A$7:$A$9,0)) -> 0.05 | J7: =INDEX(Inputs!$D$7:$D$9,MATCH(E7,Inputs!$A$7:$A$9,0)) -> 0.1 | K7: =INDEX(Inputs!$B$13:$B$15,MATCH(C7,Inputs!$A$13:$A$15,0)) -> 50000 | L7: =H7*K7 -> 1000 | M7: =I7*K7 -> 2500 | N7: =J7*K7 -> 5000 | O7: =CHOOSE(Inputs!$B$3,L7,M7,N7) -> 2500
A8: HS-01 | B8: Danbury Secondary | C8: Health and safety | D8: Asbestos management plan not updated after works | E8: High | F8: 110 | G8: No | H8: =INDEX(Inputs!$B$7:$B$9,MATCH(E8,Inputs!$A$7:$A$9,0)) -> 0.02 | I8: =INDEX(Inputs!$C$7:$C$9,MATCH(E8,Inputs!$A$7:$A$9,0)) -> 0.05 | J8: =INDEX(Inputs!$D$7:$D$9,MATCH(E8,Inputs!$A$7:$A$9,0)) -> 0.1 | K8: =INDEX(Inputs!$B$13:$B$15,MATCH(C8,Inputs!$A$13:$A$15,0)) -> 40000 | L8: =H8*K8 -> 800 | M8: =I8*K8 -> 2000 | N8: =J8*K8 -> 4000 | O8: =CHOOSE(Inputs!$B$3,L8,M8,N8) -> 2000
A9: HS-02 | B9: Ashgrove Primary | C9: Health and safety | D9: Legionella water temperature checks not recorded | E9: High | F9: 75 | G9: No | H9: =INDEX(Inputs!$B$7:$B$9,MATCH(E9,Inputs!$A$7:$A$9,0)) -> 0.02 | I9: =INDEX(Inputs!$C$7:$C$9,MATCH(E9,Inputs!$A$7:$A$9,0)) -> 0.05 | J9: =INDEX(Inputs!$D$7:$D$9,MATCH(E9,Inputs!$A$7:$A$9,0)) -> 0.1 | K9: =INDEX(Inputs!$B$13:$B$15,MATCH(C9,Inputs!$A$13:$A$15,0)) -> 40000 | L9: =H9*K9 -> 800 | M9: =I9*K9 -> 2000 | N9: =J9*K9 -> 4000 | O9: =CHOOSE(Inputs!$B$3,L9,M9,N9) -> 2000
A10: HS-03 | B10: Beacon Hill Academy | C10: Health and safety | D10: DT workshop machinery guarding inspection overdue | E10: Medium | F10: 50 | G10: Yes | H10: =INDEX(Inputs!$B$7:$B$9,MATCH(E10,Inputs!$A$7:$A$9,0)) -> 0.005 | I10: =INDEX(Inputs!$C$7:$C$9,MATCH(E10,Inputs!$A$7:$A$9,0)) -> 0.015 | J10: =INDEX(Inputs!$D$7:$D$9,MATCH(E10,Inputs!$A$7:$A$9,0)) -> 0.03 | K10: =INDEX(Inputs!$B$13:$B$15,MATCH(C10,Inputs!$A$13:$A$15,0)) -> 40000 | L10: =H10*K10 -> 200 | M10: =I10*K10 -> 600 | N10: =J10*K10 -> 1200 | O10: =CHOOSE(Inputs!$B$3,L10,M10,N10) -> 600
A11: HS-04 | B11: Elmfield Primary | C11: Health and safety | D11: Playground equipment annual inspection overdue | E11: Medium | F11: 40 | G11: No | H11: =INDEX(Inputs!$B$7:$B$9,MATCH(E11,Inputs!$A$7:$A$9,0)) -> 0.005 | I11: =INDEX(Inputs!$C$7:$C$9,MATCH(E11,Inputs!$A$7:$A$9,0)) -> 0.015 | J11: =INDEX(Inputs!$D$7:$D$9,MATCH(E11,Inputs!$A$7:$A$9,0)) -> 0.03 | K11: =INDEX(Inputs!$B$13:$B$15,MATCH(C11,Inputs!$A$13:$A$15,0)) -> 40000 | L11: =H11*K11 -> 200 | M11: =I11*K11 -> 600 | N11: =J11*K11 -> 1200 | O11: =CHOOSE(Inputs!$B$3,L11,M11,N11) -> 600
A12: HS-05 | B12: Fernwood Academy | C12: Health and safety | D12: COSHH assessments missing for cleaning products | E12: Medium | F12: 65 | G12: No | H12: =INDEX(Inputs!$B$7:$B$9,MATCH(E12,Inputs!$A$7:$A$9,0)) -> 0.005 | I12: =INDEX(Inputs!$C$7:$C$9,MATCH(E12,Inputs!$A$7:$A$9,0)) -> 0.015 | J12: =INDEX(Inputs!$D$7:$D$9,MATCH(E12,Inputs!$A$7:$A$9,0)) -> 0.03 | K12: =INDEX(Inputs!$B$13:$B$15,MATCH(C12,Inputs!$A$13:$A$15,0)) -> 40000 | L12: =H12*K12 -> 200 | M12: =I12*K12 -> 600 | N12: =J12*K12 -> 1200 | O12: =CHOOSE(Inputs!$B$3,L12,M12,N12) -> 600
A13: HS-06 | B13: Cedar Vale Primary | C13: Health and safety | D13: Accident reporting process not shared with new staff | E13: Low | F13: 30 | G13: Yes | H13: =INDEX(Inputs!$B$7:$B$9,MATCH(E13,Inputs!$A$7:$A$9,0)) -> 0 | I13: =INDEX(Inputs!$C$7:$C$9,MATCH(E13,Inputs!$A$7:$A$9,0)) -> 0 | J13: =INDEX(Inputs!$D$7:$D$9,MATCH(E13,Inputs!$A$7:$A$9,0)) -> 0.005 | K13: =INDEX(Inputs!$B$13:$B$15,MATCH(C13,Inputs!$A$13:$A$15,0)) -> 40000 | L13: =H13*K13 -> 0 | M13: =I13*K13 -> 0 | N13: =J13*K13 -> 200 | O13: =CHOOSE(Inputs!$B$3,L13,M13,N13) -> 0
... A19: DP-06 | B19: Cedar Vale Primary | C19: Data protection | D19: Supplier data processing agreements missing | E19: Medium | F19: 85 | G19: No | H19: =INDEX(Inputs!$B$7:$B$9,MATCH(E19,Inputs!$A$7:$A$9,0)) -> 0.005 | I19: =INDEX(Inputs!$C$7:$C$9,MATCH(E19,Inputs!$A$7:$A$9,0)) -> 0.015 | J19: =INDEX(Inputs!$D$7:$D$9,MATCH(E19,Inputs!$A$7:$A$9,0)) -> 0.03 | K19: =INDEX(Inputs!$B$13:$B$15,MATCH(C19,Inputs!$A$13:$A$15,0)) -> 25000 | L19: =H19*K19 -> 125 | M19: =I19*K19 -> 375 | N19: =J19*K19 -> 750 | O19: =CHOOSE(Inputs!$B$3,L19,M19,N19) -> 375
A20: Total | L20: =SUM(L2:L19) -> 8075 | M20: =SUM(M2:M19) -> 20925 | N20: =SUM(N2:N19) -> 42175 | O20: =SUM(O2:O19) -> 20925
A22: Source: fictional dataset (data/outstanding_actions.csv). Expected loss = probability of enforcement x impact, assuming the action stays unresolved for 12 months.

Sheet Options_3yr
A1: Three-year cost of each option (selected scenario)
B3: Year 1 | C3: Year 2 | D3: Year 3 | E3: Total
A4: Risk exposure if actions stay unresolved (per year) | B4: =Actions!$O$20 -> 20925 | C4: =Actions!$O$20 -> 20925 | D4: =Actions!$O$20 -> 20925 | E4: =SUM(B4:D4) -> 62775
A6: Option A: keep provider support
A7: Service fees | B7: =Inputs!$B$21 -> 11000 | C7: =B7*(1+Inputs!$B$22) -> 11330 | D7: =C7*(1+Inputs!$B$22) -> 11669.9 | E7: =SUM(B7:D7) -> 33999.9
A8: Residual risk exposure | B8: =B$4*(1-Inputs!$B$25) -> 4185 | C8: =C$4*(1-Inputs!$B$25) -> 4185 | D8: =D$4*(1-Inputs!$B$25) -> 4185 | E8: =SUM(B8:D8) -> 12555
A9: Business manager time | B9: =Inputs!$B$34*Inputs!$B$35*12 -> 840 | C9: =Inputs!$B$34*Inputs!$B$35*12 -> 840 | D9: =Inputs!$B$34*Inputs!$B$35*12 -> 840 | E9: =SUM(B9:D9) -> 2520
A10: Total cost | B10: =SUM(B7:B9) -> 16025 | C10: =SUM(C7:C9) -> 16355 | D10: =SUM(D7:D9) -> 16694.9 | E10: =SUM(B10:D10) -> 49074.9
A12: Option B: bring compliance in-house
A13: Staff cost | B13: =Inputs!$B$29*Inputs!$B$30 -> 19200 | C13: =Inputs!$B$29*Inputs!$B$30 -> 19200 | D13: =Inputs!$B$29*Inputs!$B$30 -> 19200 | E13: =SUM(B13:D13) -> 57600
A14: Training and tools | B14: =Inputs!$B$31 -> 3500 | C14: =Inputs!$B$31 -> 3500 | D14: =Inputs!$B$31 -> 3500 | E14: =SUM(B14:D14) -> 10500
A15: Residual risk exposure | B15: =B$4*(1-Inputs!$B$26) -> 10462.5 | C15: =C$4*(1-Inputs!$B$26) -> 10462.5 | D15: =D$4*(1-Inputs!$B$26) -> 10462.5 | E15: =SUM(B15:D15) -> 31387.5
A16: Business manager time | B16: =Inputs!$B$34*Inputs!$B$36*12 -> 1260 | C16: =Inputs!$B$34*Inputs!$B$36*12 -> 1260 | D16: =Inputs!$B$34*Inputs!$B$36*12 -> 1260 | E16: =SUM(B16:D16) -> 3780
A17: Total cost | B17: =SUM(B13:B16) -> 34422.5 | C17: =SUM(C13:C16) -> 34422.5 | D17: =SUM(D13:D16) -> 34422.5 | E17: =SUM(B17:D17) -> 103267.5
A19: Option C: cancel with no replacement
A20: Residual risk exposure | B20: =B$4 -> 20925 | C20: =C$4 -> 20925 | D20: =D$4 -> 20925 | E20: =SUM(B20:D20) -> 62775
A21: Business manager time | B21: =Inputs!$B$34*Inputs!$B$37*12 -> 3360 | C21: =Inputs!$B$34*Inputs!$B$37*12 -> 3360 | D21: =Inputs!$B$34*Inputs!$B$37*12 -> 3360 | E21: =SUM(B21:D21) -> 10080
A22: Total cost | B22: =SUM(B20:B21) -> 24285 | C22: =SUM(C20:C21) -> 24285 | D22: =SUM(D20:D21) -> 24285 | E22: =SUM(B22:D22) -> 72855
A24: Risk exposure is an expected value (probability x impact), not a cash cost. It shows what the trust is carrying if actions stay open.
